cell_executed_alert/__init__.py
cell_executed_alert/_version.py
cell_executed_alert/labextension/build_log.json
cell_executed_alert/labextension/package.json
cell_executed_alert/labextension/static/lib_index_js.14b203f09c1598a5b831.js
cell_executed_alert/labextension/static/lib_index_js.14b203f09c1598a5b831.js.map
cell_executed_alert/labextension/static/remoteEntry.41e3b937ba99b5beb2ad.js
cell_executed_alert/labextension/static/remoteEntry.41e3b937ba99b5beb2ad.js.map
cell_executed_alert/labextension/static/style.js
cell_executed_alert/labextension/static/style_index_js.30b61ce550f3bcb38912.js
cell_executed_alert/labextension/static/style_index_js.30b61ce550f3bcb38912.js.map
cell_executed_alert/labextension/static/vendors-node_modules_css-loader_dist_runtime_api_js-node_modules_css-loader_dist_runtime_cssW-926fd9.d5a4e27364c828ef27ca.js
cell_executed_alert/labextension/static/vendors-node_modules_css-loader_dist_runtime_api_js-node_modules_css-loader_dist_runtime_cssW-926fd9.d5a4e27364c828ef27ca.js.map
cell_executed_alert-0.1.2.data/data/share/jupyter/labextensions/cell-executed-alert/build_log.json
cell_executed_alert-0.1.2.data/data/share/jupyter/labextensions/cell-executed-alert/install.json
cell_executed_alert-0.1.2.data/data/share/jupyter/labextensions/cell-executed-alert/package.json
cell_executed_alert-0.1.2.data/data/share/jupyter/labextensions/cell-executed-alert/static/lib_index_js.14b203f09c1598a5b831.js
cell_executed_alert-0.1.2.data/data/share/jupyter/labextensions/cell-executed-alert/static/lib_index_js.14b203f09c1598a5b831.js.map
cell_executed_alert-0.1.2.data/data/share/jupyter/labextensions/cell-executed-alert/static/remoteEntry.41e3b937ba99b5beb2ad.js
cell_executed_alert-0.1.2.data/data/share/jupyter/labextensions/cell-executed-alert/static/remoteEntry.41e3b937ba99b5beb2ad.js.map
cell_executed_alert-0.1.2.data/data/share/jupyter/labextensions/cell-executed-alert/static/style.js
cell_executed_alert-0.1.2.dist-info/LICENSE
cell_executed_alert-0.1.2.dist-info/METADATA
cell_executed_alert-0.1.2.dist-info/WHEEL
cell_executed_alert-0.1.2.dist-info/top_level.txt
cell_executed_alert-0.1.2.dist-info/RECORD
